oslo_serialization/__init__.py
oslo_serialization/base64.py
oslo_serialization/jsonutils.py
oslo_serialization/msgpackutils.py
oslo_serialization/serializer/__init__.py
oslo_serialization/serializer/base_serializer.py
oslo_serialization/serializer/json_serializer.py
oslo_serialization/serializer/msgpack_serializer.py
oslo_serialization/tests/__init__.py
oslo_serialization/tests/test_base64.py
oslo_serialization/tests/test_jsonutils.py
oslo_serialization/tests/test_msgpackutils.py
oslo.serialization-5.7.0.dist-info/AUTHORS
oslo.serialization-5.7.0.dist-info/LICENSE
oslo.serialization-5.7.0.dist-info/METADATA
oslo.serialization-5.7.0.dist-info/WHEEL
oslo.serialization-5.7.0.dist-info/pbr.json
oslo.serialization-5.7.0.dist-info/top_level.txt
oslo.serialization-5.7.0.dist-info/RECORD
